Neural_Decoding/__init__.py
Neural_Decoding/decoders.py
Neural_Decoding/metrics.py
Neural_Decoding/preprocessing_funcs.py
Neural_Decoding-0.1.5.dist-info/LICENSE
Neural_Decoding-0.1.5.dist-info/METADATA
Neural_Decoding-0.1.5.dist-info/WHEEL
Neural_Decoding-0.1.5.dist-info/top_level.txt
Neural_Decoding-0.1.5.dist-info/RECORD
