Metadata-Version: 2.1
Name: Neural-Decoding
Version: 0.1.5
Summary: A python package that includes many methods for decoding neural activity.
Home-page: UNKNOWN
Maintainer: Josh Glaser
Maintainer-email: joshglaser88@gmail.com 
License: BSD 3-Clause License
Download-URL: https://github.com/KordingLab/Neural_Decoding.git
Platform: any
Classifier: Intended Audience :: Science/Research
Classifier: Intended Audience :: Developers
Classifier: License :: OSI Approved
Classifier: Programming Language :: Python
Classifier: Topic :: Software Development
Classifier: Topic :: Scientific/Engineering
Classifier: Operating System :: Microsoft :: Windows
Classifier: Operating System :: POSIX
Classifier: Operating System :: Unix
Classifier: Operating System :: MacOS
Requires-Dist: numpy (>=1.16.3)
